{
	"$schema": "http://schema.management.azure.com/schemas/2015-01-01/deploymentTemplate.json#",
	"contentVersion": "1.0.0.0",
	"parameters": {
		"factoryName": {
			"type": "string",
			"metadata": "Data Factory name",
			"defaultValue": "eal-adf-d"
		}
	},
	"variables": {
		"factoryId": "[concat('Microsoft.DataFactory/factories/', parameters('factoryName'))]"
	},
	"resources": [
		{
			"name": "[concat(parameters('factoryName'), '/eal_adf_cntrl')]",
			"type": "Microsoft.DataFactory/factories/datasets",
			"apiVersion": "2018-06-01",
			"properties": {
				"linkedServiceName": {
					"referenceName": "eal_sqldb_STG",
					"type": "LinkedServiceReference"
				},
				"folder": {
					"name": "Destination Table/Staging"
				},
				"annotations": [],
				"type": "AzureSqlTable",
				"schema": [
					{
						"name": "ADF_RUN_ID",
						"type": "varchar"
					},
					{
						"name": "ADF_JOB_NAME",
						"type": "varchar"
					},
					{
						"name": "ADF_SUC_TS",
						"type": "date"
					}
				],
				"typeProperties": {
					"schema": "dbo",
					"table": "S_ADF_CNTRL"
				}
			},
			"dependsOn": []
		},
		{
			"name": "[concat(parameters('factoryName'), '/adf_control')]",
			"type": "Microsoft.DataFactory/factories/dataflows",
			"apiVersion": "2018-06-01",
			"properties": {
				"folder": {
					"name": "ADF Control Table"
				},
				"type": "MappingDataFlow",
				"typeProperties": {
					"sources": [
						{
							"dataset": {
								"referenceName": "ADF_Control",
								"type": "DatasetReference"
							},
							"name": "ADFCONTROL"
						}
					],
					"sinks": [
						{
							"dataset": {
								"referenceName": "eal_adf_cntrl",
								"type": "DatasetReference"
							},
							"name": "Write"
						}
					],
					"transformations": [
						{
							"name": "AddADFDetails"
						},
						{
							"name": "AlterRow"
						}
					],
					"script": "parameters{\n\trun_id as string (''),\n\tadf_name as string ('')\n}\nsource(output(\n\t\trow as string\n\t),\n\tallowSchemaDrift: true,\n\tvalidateSchema: false,\n\tignoreNoFilesFound: false,\n\tdocumentForm: 'documentPerLine') ~> ADFCONTROL\nADFCONTROL derive(ADF_RUN_ID = $run_id,\n\t\tADF_TIME_STMP = currentDate()-1,\n\t\tADF_JOB_NAME = $adf_name) ~> AddADFDetails\nAddADFDetails alterRow(updateIf(ADF_JOB_NAME==$adf_name)) ~> AlterRow\nAlterRow sink(input(\n\t\tADF_RUN_ID as string,\n\t\tADF_JOB_NAME as string,\n\t\tADF_SUC_TS as date\n\t),\n\tallowSchemaDrift: true,\n\tvalidateSchema: false,\n\tdeletable:false,\n\tinsertable:true,\n\tupdateable:true,\n\tupsertable:false,\n\tkeys:['ADF_JOB_NAME'],\n\tformat: 'table',\n\tmapColumn(\n\t\tADF_RUN_ID,\n\t\tADF_JOB_NAME,\n\t\tADF_SUC_TS = ADF_TIME_STMP\n\t),\n\tskipDuplicateMapInputs: true,\n\tskipDuplicateMapOutputs: true,\n\terrorHandlingOption: 'stopOnFirstError') ~> Write"
				}
			},
			"dependsOn": [
				"[concat(variables('factoryId'), '/datasets/eal_adf_cntrl')]"
			]
		},
		{
			"name": "[concat(parameters('factoryName'), '/adf_reset_dataflow')]",
			"type": "Microsoft.DataFactory/factories/dataflows",
			"apiVersion": "2018-06-01",
			"properties": {
				"folder": {
					"name": "ADF Control Table"
				},
				"type": "MappingDataFlow",
				"typeProperties": {
					"sources": [
						{
							"dataset": {
								"referenceName": "eal_adf_cntrl",
								"type": "DatasetReference"
							},
							"name": "GetControls"
						}
					],
					"sinks": [
						{
							"dataset": {
								"referenceName": "eal_adf_cntrl",
								"type": "DatasetReference"
							},
							"name": "WriteResetDate"
						}
					],
					"transformations": [
						{
							"name": "AlterRow"
						},
						{
							"name": "FilterJob"
						},
						{
							"name": "ResetDate"
						}
					],
					"script": "parameters{\n\tjob_name as string ('')\n}\nsource(output(\n\t\tADF_RUN_ID as string,\n\t\tADF_JOB_NAME as string,\n\t\tADF_SUC_TS as timestamp\n\t),\n\tallowSchemaDrift: true,\n\tvalidateSchema: false,\n\tignoreNoFilesFound: false,\n\tisolationLevel: 'READ_UNCOMMITTED',\n\tformat: 'table') ~> GetControls\nResetDate alterRow(updateIf(ADF_JOB_NAME==$job_name)) ~> AlterRow\nGetControls filter(ADF_JOB_NAME == $job_name) ~> FilterJob\nFilterJob derive(Date = '1899-01-01 00:00:00.000',\n\t\tid = '') ~> ResetDate\nAlterRow sink(input(\n\t\tADF_RUN_ID as string,\n\t\tADF_JOB_NAME as string,\n\t\tADF_SUC_TS as date\n\t),\n\tallowSchemaDrift: true,\n\tvalidateSchema: false,\n\tdeletable:false,\n\tinsertable:false,\n\tupdateable:true,\n\tupsertable:false,\n\tkeys:['ADF_JOB_NAME'],\n\tformat: 'table',\n\tmapColumn(\n\t\tADF_RUN_ID = id,\n\t\tADF_JOB_NAME,\n\t\tADF_SUC_TS = Date\n\t),\n\tskipDuplicateMapInputs: true,\n\tskipDuplicateMapOutputs: true,\n\terrorHandlingOption: 'stopOnFirstError') ~> WriteResetDate"
				}
			},
			"dependsOn": [
				"[concat(variables('factoryId'), '/datasets/eal_adf_cntrl')]"
			]
		}
	]
}